<?xml version="1.0" encoding="UTF-8" standalone="no"?><CONTRACT><HEADERS><PLACE_DATE>07.08.2018</PLACE_DATE><FIRST_SIDE/><SECOND_SIDE/></HEADERS><GENERAL><TYPE>umowa o pracę</TYPE><SIDES><FIRST_SIDE><COMPANY>true</COMPANY><NAME>Prezes Zarządu</NAME><ADDRESS>ul. Główny 8</ADDRESS><CITY>Poznań</CITY><REGON/><NIP/><REPRESENTATIVE>Kazimierz Boroń</REPRESENTATIVE><ROLE>pracodawca</ROLE></FIRST_SIDE><SECOND_SIDE><COMPANY>false</COMPANY><NAME>Adam Nowak</NAME><ADDRESS>ul. Rybnicki 9</ADDRESS><CITY>Poznań</CITY><PESEL/><ID/><ROLE>Pracownikiem</ROLE></SECOND_SIDE></SIDES><CONCLUSION_PLACE>Poznań</CONCLUSION_PLACE><CONCLUSION_DATE>07.08.2018</CONCLUSION_DATE></GENERAL><DETAILS><CONTRACT_PERIOD>czas nieokreślony</CONTRACT_PERIOD><DEFINITE_PERIOD/><HOURLY_DIMENSION>pełny etat</HOURLY_DIMENSION><PART_TIME_DIMENSION>1</PART_TIME_DIMENSION><POSITION>administrator</POSITION><WORKING_PLACE>ul. Dworcowy 10</WORKING_PLACE><START_DATE>10.08.2018</START_DATE><WORKING_HOURS/><SALARY>2852 złoty</SALARY></DETAILS></CONTRACT>