<?xml version="1.0" encoding="UTF-8" standalone="no"?><CONTRACT><HEADERS><PLACE_DATE>17.09.2008</PLACE_DATE><FIRST_SIDE/><SECOND_SIDE/></HEADERS><GENERAL><TYPE>umowa o pracę</TYPE><SIDES><FIRST_SIDE><COMPANY>true</COMPANY><NAME>Piękne</NAME><ADDRESS/><CITY/><REGON/><NIP/><REPRESENTATIVE/><ROLE/></FIRST_SIDE><SECOND_SIDE><COMPANY>false</COMPANY><NAME>Katarzyna Strzelecka</NAME><ADDRESS/><CITY/><PESEL/><ID/><ROLE/></SECOND_SIDE></SIDES><CONCLUSION_PLACE/><CONCLUSION_DATE>1.03.2008</CONCLUSION_DATE></GENERAL><DETAILS><CONTRACT_PERIOD>inny</CONTRACT_PERIOD><DEFINITE_PERIOD>1 rok</DEFINITE_PERIOD><HOURLY_DIMENSION>pełny etat</HOURLY_DIMENSION><PART_TIME_DIMENSION>1</PART_TIME_DIMENSION><POSITION/><WORKING_PLACE/><START_DATE/><WORKING_HOURS/><SALARY/></DETAILS></CONTRACT>